data_agent_tunnel_client/__init__.py
data_agent_tunnel_client/auth.py
data_agent_tunnel_client/cli.py
data_agent_tunnel_client/client.py
data_agent_tunnel_client/integration.py
examples/fastapi_example.py
examples/flask_example.py
data_agent_tunnel_client-0.1.8.dist-info/METADATA
data_agent_tunnel_client-0.1.8.dist-info/WHEEL
data_agent_tunnel_client-0.1.8.dist-info/entry_points.txt
data_agent_tunnel_client-0.1.8.dist-info/top_level.txt
data_agent_tunnel_client-0.1.8.dist-info/RECORD
