Metadata-Version: 2.4
Name: data-agent-tunnel-client
Version: 0.1.8
Summary: Data Agent Tunnel client - proxy local web services to public network
Author: EigenAI
License-Expression: MIT
Classifier: Development Status :: 4 - Beta
Classifier: Intended Audience :: Developers
Classifier: Programming Language :: Python :: 3
Classifier: Programming Language :: Python :: 3.8
Classifier: Programming Language :: Python :: 3.9
Classifier: Programming Language :: Python :: 3.10
Classifier: Programming Language :: Python :: 3.11
Classifier: Programming Language :: Python :: 3.12
Requires-Python: >=3.8
Requires-Dist: websockets>=10.0
Requires-Dist: aiohttp>=3.8.0
Provides-Extra: dev
Requires-Dist: pytest>=7.0; extra == "dev"
Requires-Dist: pytest-asyncio>=0.20; extra == "dev"
Provides-Extra: examples
Requires-Dist: flask>=2.0.0; extra == "examples"
Requires-Dist: fastapi>=0.100.0; extra == "examples"
Requires-Dist: uvicorn>=0.20.0; extra == "examples"
